{
  "type": "FeatureCollection",
  "data": {
    "start": {
      "year": 1378,
      "month": null,
      "day": null
    },
    "end": {
      "year": 1502,
      "month": null,
      "day": null
    },
    "ar": {
      "name": "الآق قويونلو",
      "description": "الآق قويونلو، الآغ قويونلو، الخرفان البيض: من القبائل التركمانية، حكمت في شرق الأناضول، أذربيجان، فارس، العراق، أفغانستان وتركستان ما بين 1467-1502 م. عرقيا تنحدر القبيلة من الأتراك الأغوز أو ما يعرف بالغز. بعد سنة 1490 م بدأ الصراع مع الصفويين الذين استطاعوا أن يجلو الخرفان البيض عن تبريز سنة 1501 م. بدأت بعد ذلك مرحلة الانحلال. استقر آخر الحكام في ماردين حتى 1507 م.",
      "link": "http://ar.wikipedia.org/wiki/%D8%A7%D9%82_%D9%82%D9%88%D9%8A%D9%88%D9%86%D9%84%D9%88",
      "ref": "http://en.wikipedia.org/wiki/Aq_Qoyunlu"
    }
  },
  "features": [
    {
      "type": "Feature",
      "properties": {
        "start": {
          "year": 1378,
          "month": null,
          "day": null
        },
        "end": {
          "year": 1398,
          "month": null,
          "day": null
        },
        "ar": {
          "description": "قيام الدولة"
        }
      },
      "geometry": {
        "type": "MultiPolygon",
        "coordinates": [
          [
            [
              [
                41.8200073577,
                41.1745193556
              ],
              [
                39.4249878265,
                40.1284910569
              ],
              [
                39.4969483092,
                39.7071866568
              ],
              [
                39.211303778,
                38.68550976
              ],
              [
                38.2884522155,
                38.324420427
              ],
              [
                40.2269897796,
                37.9008650926
              ],
              [
                43.430053778,
                38.4965935189
              ],
              [
                42.6989136077,
                41.1041909446
              ],
              [
                41.5563354827,
                41.5414776668
              ],
              [
                41.8200073577,
                41.1745193556
              ]
            ]
          ]
        ]
      }
    },
    {
      "type": "Feature",
      "properties": {
        "start": {
          "year": 1398,
          "month": null,
          "day": null
        },
        "end": {
          "year": 1401,
          "month": null,
          "day": null
        },
        "ar": {
          "description": "سقوط آل آرتين"
        }
      },
      "geometry": {
        "type": "MultiPolygon",
        "coordinates": [
          [
            [
              [
                41.8200073577,
                41.1745193556
              ],
              [
                39.4249878265,
                40.1284910569
              ],
              [
                38.4032593109,
                40.9218144124
              ],
              [
                37.4364622682,
                41.0710691308
              ],
              [
                36.332885474,
                41.2943172632
              ],
              [
                35.953308139,
                41.7303300505
              ],
              [
                35.8324585296,
                40.6556387401
              ],
              [
                35.4778746888,
                38.7283759182
              ],
              [
                38.2884522155,
                38.324420427
              ],
              [
                40.2269897796,
                37.9008650926
              ],
              [
                43.4080811217,
                38.4793946733
              ],
              [
                42.6989136077,
                41.1041909446
              ],
              [
                41.5563354827,
                41.5414776668
              ],
              [
                41.8200073577,
                41.1745193556
              ]
            ]
          ]
        ]
      }
    },
    {
      "type": "Feature",
      "properties": {
        "start": {
          "year": 1401,
          "month": null,
          "day": null
        },
        "end": {
          "year": 1460,
          "month": null,
          "day": null
        },
        "ar": {
          "description": "الاق قويونلو حكام على ديار بكر من قبل التيموريين"
        }
      },
      "geometry": {
        "type": "MultiPolygon",
        "coordinates": [
          [
            [
              [
                39.023437125,
                39.5972236022
              ],
              [
                36.914062125,
                37.5794128808
              ],
              [
                38.9465328281,
                36.6948513133
              ],
              [
                42.7038570469,
                37.1428038133
              ],
              [
                40.5065914219,
                40.9881919134
              ],
              [
                39.7045894687,
                40.9716038828
              ],
              [
                39.023437125,
                39.5972236022
              ]
            ]
          ]
        ]
      }
    },
    {
      "type": "Feature",
      "properties": {
        "start": {
          "year": 1460,
          "month": null,
          "day": null
        },
        "end": {
          "year": 1469,
          "month": null,
          "day": null
        },
        "ar": {
          "description": "توسع العثمانيين"
        }
      },
      "geometry": {
        "type": "MultiPolygon",
        "coordinates": [
          [
            [
              [
                39.023437125,
                39.5972236022
              ],
              [
                36.914062125,
                37.5794128808
              ],
              [
                38.9465328281,
                36.6948513133
              ],
              [
                42.7038570469,
                37.1428038133
              ],
              [
                41.2426754062,
                39.9013089414
              ],
              [
                39.023437125,
                39.5972236022
              ]
            ]
          ]
        ]
      }
    },
    {
      "type": "Feature",
      "properties": {
        "start": {
          "year": 1469,
          "month": null,
          "day": null
        },
        "end": {
          "year": 1474,
          "month": null,
          "day": null
        },
        "ar": {
          "description": "الاق قويونلو يسيطرون على اراضي القراقيونلو"
        }
      },
      "geometry": {
        "type": "MultiPolygon",
        "coordinates": [
          [
            [
              [
                39.023437125,
                39.5972236022
              ],
              [
                36.914062125,
                37.5794128808
              ],
              [
                38.9465328281,
                36.6948513133
              ],
              [
                40.4681392734,
                35.0120024229
              ],
              [
                40.2703853672,
                33.0270879687
              ],
              [
                45.3021236484,
                31.2785512552
              ],
              [
                47.8948970859,
                29.9930026861
              ],
              [
                48.4442134922,
                29.9739706421
              ],
              [
                49.9822994297,
                30.1451275843
              ],
              [
                51.4984127109,
                27.9167670509
              ],
              [
                52.5091548984,
                27.7418850428
              ],
              [
                53.7615963047,
                26.7456107962
              ],
              [
                54.7943111484,
                26.4705734374
              ],
              [
                55.6951900547,
                29.4395979703
              ],
              [
                53.3880611484,
                35.5858519703
              ],
              [
                52.3992916172,
                36.4389616138
              ],
              [
                49.8944088047,
                37.4574184706
              ],
              [
                49.0155025547,
                37.6664295791
              ],
              [
                48.8616939609,
                38.7369464273
              ],
              [
                49.8724361484,
                40.4302239874
              ],
              [
                47.4993892734,
                42.9564228504
              ],
              [
                46.9281002109,
                44.7545358134
              ],
              [
                38.0511470859,
                44.5826431498
              ],
              [
                39.9078365391,
                43.3970655762
              ],
              [
                41.4569088047,
                42.7228040979
              ],
              [
                41.7974849766,
                41.8859213733
              ],
              [
                41.5118404453,
                41.5332544898
              ],
              [
                42.7313228672,
                41.5003499385
              ],
              [
                41.22070275,
                39.9013089414
              ],
              [
                39.023437125,
                39.5972236022
              ]
            ]
          ]
        ]
      }
    },
    {
      "type": "Feature",
      "properties": {
        "start": {
          "year": 1474,
          "month": null,
          "day": null
        },
        "end": {
          "year": 1475,
          "month": null,
          "day": null
        },
        "ar": {
          "description": "العثمانيين"
        }
      },
      "geometry": {
        "type": "MultiPolygon",
        "coordinates": [
          [
            [
              [
                41.5063472812,
                38.7455155465
              ],
              [
                37.35351525,
                37.0551774766
              ],
              [
                38.9465328281,
                36.6948513133
              ],
              [
                40.4681392734,
                35.0120024229
              ],
              [
                40.2703853672,
                33.0270879687
              ],
              [
                45.3021236484,
                31.2785512552
              ],
              [
                47.8948970859,
                29.9930026861
              ],
              [
                48.4442134922,
                29.9739706421
              ],
              [
                49.9822994297,
                30.1451275843
              ],
              [
                51.4984127109,
                27.9167670509
              ],
              [
                52.5091548984,
                27.7418850428
              ],
              [
                53.7615963047,
                26.7456107962
              ],
              [
                54.7943111484,
                26.4705734374
              ],
              [
                55.6951900547,
                29.4395979703
              ],
              [
                53.3880611484,
                35.5858519703
              ],
              [
                52.3992916172,
                36.4389616138
              ],
              [
                49.8944088047,
                37.4574184706
              ],
              [
                49.0155025547,
                37.6664295791
              ],
              [
                48.8616939609,
                38.7369464273
              ],
              [
                49.8724361484,
                40.4302239874
              ],
              [
                47.4993892734,
                42.9564228504
              ],
              [
                46.9281002109,
                44.7545358134
              ],
              [
                38.0511470859,
                44.5826431498
              ],
              [
                39.9078365391,
                43.3970655762
              ],
              [
                41.4569088047,
                42.7228040979
              ],
              [
                41.7974849766,
                41.8859213733
              ],
              [
                41.5118404453,
                41.5332544898
              ],
              [
                42.7313228672,
                41.5003499385
              ],
              [
                41.5063472812,
                38.7455155465
              ]
            ]
          ]
        ]
      }
    },
    {
      "type": "Feature",
      "properties": {
        "start": {
          "year": 1475,
          "month": null,
          "day": null
        },
        "end": {
          "year": 1502,
          "month": null,
          "day": null
        },
        "ar": {
          "description": "العثمانيين"
        }
      },
      "geometry": {
        "type": "MultiPolygon",
        "coordinates": [
          [
            [
              [
                41.5063472812,
                38.7455155465
              ],
              [
                37.35351525,
                37.0551774766
              ],
              [
                38.9465328281,
                36.6948513133
              ],
              [
                40.4681392734,
                35.0120024229
              ],
              [
                40.2703853672,
                33.0270879687
              ],
              [
                45.3021236484,
                31.2785512552
              ],
              [
                47.8948970859,
                29.9930026861
              ],
              [
                48.4442134922,
                29.9739706421
              ],
              [
                49.9822994297,
                30.1451275843
              ],
              [
                51.4984127109,
                27.9167670509
              ],
              [
                52.5091548984,
                27.7418850428
              ],
              [
                53.7615963047,
                26.7456107962
              ],
              [
                54.7943111484,
                26.4705734374
              ],
              [
                55.6951900547,
                29.4395979703
              ],
              [
                53.3880611484,
                35.5858519703
              ],
              [
                52.3992916172,
                36.4389616138
              ],
              [
                49.8944088047,
                37.4574184706
              ],
              [
                49.0155025547,
                37.6664295791
              ],
              [
                48.8616939609,
                38.7369464273
              ],
              [
                49.8724361484,
                40.4302239874
              ],
              [
                47.4993892734,
                42.9564228504
              ],
              [
                46.9281002109,
                44.7545358134
              ],
              [
                41.4486690586,
                44.6413001906
              ],
              [
                39.9078365391,
                43.3970655762
              ],
              [
                41.4569088047,
                42.7228040979
              ],
              [
                41.7974849766,
                41.8859213733
              ],
              [
                41.5118404453,
                41.5332544898
              ],
              [
                42.7313228672,
                41.5003499385
              ],
              [
                41.5063472812,
                38.7455155465
              ]
            ]
          ]
        ]
      }
    }
  ]
}